Classfile /Users/samtebbs/Documents/GitRepos/ash/classes/Tuple2.class
  Last modified 15-Jul-2015; size 414 bytes
  MD5 checksum f94db2d4358ab2ecc37e2ec0755cffee
  Compiled from "Tuple2.ash"
public class Tuple2<A extends java.lang.Object, B extends java.lang.Object> extends java.lang.Object
  minor version: 0
  major version: 52
  flags: ACC_PUBLIC, ACC_SUPER
Constant pool:
   #1 = Utf8               Tuple2
   #2 = Class              #1             // Tuple2
   #3 = Utf8               <A:Ljava/lang/Object;B:Ljava/lang/Object;>Ljava/lang/Object;
   #4 = Utf8               Ljava/lang/Object;
   #5 = Class              #4             // "Ljava/lang/Object;"
   #6 = Utf8               Tuple2.ash
   #7 = Utf8               a
   #8 = Utf8               TA;
   #9 = Utf8               b
  #10 = Utf8               TB;
  #11 = Utf8               Tuple2.<init>
  #12 = Utf8               (Ljava/lang/Object;Ljava/lang/Object;)V
  #13 = Utf8               aArg
  #14 = NameAndType        #7:#4          // a:Ljava/lang/Object;
  #15 = Fieldref           #2.#14         // Tuple2.a:Ljava/lang/Object;
  #16 = Utf8               bArg
  #17 = NameAndType        #9:#4          // b:Ljava/lang/Object;
  #18 = Fieldref           #2.#17         // Tuple2.b:Ljava/lang/Object;
  #19 = Utf8               Signature
  #20 = Utf8               Code
  #21 = Utf8               LocalVariableTable
  #22 = Utf8               SourceFile
{
  public A a;
    descriptor: Ljava/lang/Object;
    flags: ACC_PUBLIC
    Signature: #8                           // TA;

  public B b;
    descriptor: Ljava/lang/Object;
    flags: ACC_PUBLIC
    Signature: #10                          // TB;

  public void Tuple2.<init>(java.lang.Object, java.lang.Object);
    descriptor: (Ljava/lang/Object;Ljava/lang/Object;)V
    flags: ACC_PUBLIC
    Code:
      stack=4, locals=3, args_size=3
         0: aload_0
         1: aload_1
         2: putfield      #15                 // Field a:Ljava/lang/Object;
         5: aload_0
         6: aload_2
         7: putfield      #18                 // Field b:Ljava/lang/Object;
        10: return
      LocalVariableTable:
        Start  Length  Slot  Name   Signature
            0       0     1  aArg   Ljava/lang/Object;
            5       0     2  bArg   Ljava/lang/Object;
}
Signature: #3                           // <A:Ljava/lang/Object;B:Ljava/lang/Object;>Ljava/lang/Object;
SourceFile: "Tuple2.ash"